LICENSE
MANIFEST.in
README.rst
bootstrap.py
buildout.cfg
setup.py
versions.cfg
demo_zinnia_twitter/__init__.py
demo_zinnia_twitter/settings.py
demo_zinnia_twitter/urls.py
zinnia_twitter/__init__.py
zinnia_twitter/admin.py
zinnia_twitter/settings.py
zinnia_twitter.egg-info/PKG-INFO
zinnia_twitter.egg-info/SOURCES.txt
zinnia_twitter.egg-info/dependency_links.txt
zinnia_twitter.egg-info/not-zip-safe
zinnia_twitter.egg-info/requires.txt
zinnia_twitter.egg-info/top_level.txt
zinnia_twitter/management/__init__.py
zinnia_twitter/management/commands/__init__.py
zinnia_twitter/management/commands/get_twitter_access.py