Metadata-Version: 1.1
Name: zinnia-twitter
Version: 1.1
Summary: Twitter plugin for django-blog-zinnia
Home-page: https://github.com/Fantomas42/zinnia-twitter
Author: Fantomas42
Author-email: fantomas42@gmail.com
License: BSD License
Keywords: django,zinnia,twitter
Platform: UNKNOWN
Classifier: Framework :: Django
Classifier: Development Status :: 5 - Production/Stable
Classifier: Environment :: Web Environment
Classifier: Programming Language :: Python
Classifier: Programming Language :: Python :: 3
Classifier: Intended Audience :: Developers
Classifier: Operating System :: OS Independent
Classifier: License :: OSI Approved :: BSD License
Classifier: Topic :: Software Development :: Libraries :: Python Modules
